pdb_profiling/__init__.py
pdb_profiling/cif_gz_stream.py
pdb_profiling/data.py
pdb_profiling/ensure.py
pdb_profiling/exceptions.py
pdb_profiling/log.py
pdb_profiling/utils.py
pdb_profiling/validate.py
pdb_profiling/viewer.py
pdb_profiling/warnings.py
pdb_profiling/commands/__init__.py
pdb_profiling/commands/_interface.py
pdb_profiling/commands/command.py
pdb_profiling/cython/__init__.py
pdb_profiling/cython/align.py
pdb_profiling/cython/cyrange.c
pdb_profiling/cython/cyrange.cp37-win_amd64.pyd
pdb_profiling/cython/cyrange.pyx
pdb_profiling/cython/py_qcprot.c
pdb_profiling/cython/py_qcprot.cp37-win_amd64.pyd
pdb_profiling/cython/py_qcprot.pyx
pdb_profiling/cython/qcprot.c
pdb_profiling/cython/qcprot.h
pdb_profiling/fetcher/__init__.py
pdb_profiling/fetcher/_dbfetch.py
pdb_profiling/fetcher/webfetch.py
pdb_profiling/pipelines/_score.py
pdb_profiling/pipelines/_select.py
pdb_profiling/processors/__init__.py
pdb_profiling/processors/database.py
pdb_profiling/processors/recordbase.py
pdb_profiling/processors/transformer.py
pdb_profiling/processors/ensembl/__init__.py
pdb_profiling/processors/ensembl/api.py
pdb_profiling/processors/eutils/__init__.py
pdb_profiling/processors/eutils/api.py
pdb_profiling/processors/i3d/__init__.py
pdb_profiling/processors/i3d/api.py
pdb_profiling/processors/pdbe/__init__.py
pdb_profiling/processors/pdbe/_sqlite_api.py
pdb_profiling/processors/pdbe/api.py
pdb_profiling/processors/pdbe/neo4j_api.py
pdb_profiling/processors/pdbe/record.py
pdb_profiling/processors/proteins/__init__.py
pdb_profiling/processors/proteins/api.py
pdb_profiling/processors/proteins/record.py
pdb_profiling/processors/rcsb/__init__.py
pdb_profiling/processors/rcsb/api.py
pdb_profiling/processors/swissmodel/__init__.py
pdb_profiling/processors/swissmodel/api.py
pdb_profiling/processors/uniprot/__init__.py
pdb_profiling/processors/uniprot/_process.py
pdb_profiling/processors/uniprot/api.py
pdb_profiling/processors/uniprot/record.py
pdb_profiling-0.3.4.dist-info/LICENSE
pdb_profiling-0.3.4.dist-info/METADATA
pdb_profiling-0.3.4.dist-info/WHEEL
pdb_profiling-0.3.4.dist-info/entry_points.txt
pdb_profiling-0.3.4.dist-info/top_level.txt
pdb_profiling-0.3.4.dist-info/RECORD
