Metadata-Version: 2.1
Name: pdb-profiling
Version: 0.3.4
Summary: Profiling Protein Structures from Protein Data Bank and integrate various resources.🏄‍♂️
Home-page: https://github.com/NatureGeorge/pdb-profiling
Author-email: hydrozzf@qq.com
Maintainer: ZeFeng Zhu
Maintainer-email: hydrozzf@qq.com
License: MIT
Platform: UNKNOWN
Classifier: Operating System :: OS Independent
Classifier: Programming Language :: Python :: 3.7
Classifier: Programming Language :: Python :: 3.8
Requires-Python: >=3.7.*
Requires-Dist: aioftp (>=0.18.1)
Requires-Dist: aiohttp (>=3.7.4)
Requires-Dist: aiofiles (>=0.6.0)
Requires-Dist: unsync (>=1.2.1)
Requires-Dist: tenacity (>=6.3.0)
Requires-Dist: orjson (>=3.0.2)
Requires-Dist: pyexcel (>=0.6.4)
Requires-Dist: pandas (>=1.1.5)
Requires-Dist: numpy (>=1.19.2)
Requires-Dist: textdistance (>=4.2.0)
Requires-Dist: databases[sqlite] (==0.4.3)
Requires-Dist: rich (>=9.5.0)
Requires-Dist: orm (==0.1.5)
Requires-Dist: sqlalchemy (==1.3.13)
Requires-Dist: scikit-learn (>=0.23.2)
Requires-Dist: python-slugify (>=4.0.0)
Requires-Dist: cachetools (>=4.1.0)
Requires-Dist: click (>=7.1.2)
Requires-Dist: parasail (>=1.2.4)
